webcomponentsscan/__init__.py
webcomponentsscan/web_components_scan.py
webcomponentsscan-1.0.1.dist-info/LICENSE
webcomponentsscan-1.0.1.dist-info/METADATA
webcomponentsscan-1.0.1.dist-info/WHEEL
webcomponentsscan-1.0.1.dist-info/RECORD
